README.txt
setup.py
blockdiagcontrib_excelshape/__init__.py
blockdiagcontrib_excelshape/excelshape.py
blockdiagcontrib_excelshape.egg-info/PKG-INFO
blockdiagcontrib_excelshape.egg-info/SOURCES.txt
blockdiagcontrib_excelshape.egg-info/dependency_links.txt
blockdiagcontrib_excelshape.egg-info/entry_points.txt
blockdiagcontrib_excelshape.egg-info/namespace_packages.txt
blockdiagcontrib_excelshape.egg-info/requires.txt
blockdiagcontrib_excelshape.egg-info/top_level.txt