Metadata-Version: 1.1
Name: blockdiagcontrib-excelshape
Version: 0.1.0
Summary: imagedrawer plugin for blockdiag
Home-page: http://bitbucket.org/mzp/blockdiagcontrib-excelshape
Author: MIZUNO Hiroki
Author-email: mzpppp at gmail.com
License: Apache License 2.0
Keywords: diagram,generator
Platform: UNKNOWN
Classifier: Development Status :: 4 - Beta
Classifier: Intended Audience :: System Administrators
Classifier: License :: OSI Approved :: Python Software Foundation License
Classifier: Programming Language :: Python
Classifier: Topic :: Software Development
Classifier: Topic :: Software Development :: Documentation
Classifier: Topic :: Text Processing :: Markup
